assignment1_pattern_recognisation/FirstAssignmentBehavioral/testBench.v
`timescale 1ns / 1ps
//////////////////////////////////////////////////////////////////////////////////
// Company: 
// Engineer: 
// 
// Create Date:    11:00:33 07/28/2017 
// Design Name: 
// Module Name:    testBench 
// Project Name: 
// Target Devices: 
// Tool versions: 
// Description: 
//
// Dependencies: 
//
// Revision: 
// Revision 0.01 - File Created
// Additional Comments: 
//
//////////////////////////////////////////////////////////////////////////////////
module testBench (inp, clk);

	integer seed;
	output clk;
	output inp;
  
  	reg inp;
  	reg clk;
	
	initial begin
		seed = 0;
      	clk = 1;
      	#15000 $finish;
	end

	always begin
		#500 inp = $random(seed);
	end
  
  	always begin
      	#250 clk = !clk;
    end

endmodule

assignment1_pattern_recognisation/FirstAssignmentBehavioral/delayElem_beh.v
`timescale 1ns / 1ps
//////////////////////////////////////////////////////////////////////////////////
// Company: 
// Engineer: 
// 
// Create Date:    10:59:36 07/28/2017 
// Design Name: 
// Module Name:    delayElem_beh 
// Project Name: 
// Target Devices: 
// Tool versions: 
// Description: 
//
// Dependencies: 
//
// Revision: 
// Revision 0.01 - File Created
// Additional Comments: 
//
//////////////////////////////////////////////////////////////////////////////////
module delayElem_beh (si, so, clk);

	input clk;
	input [1:0] so;
	output [1:0] si;
	
	reg [1:0] si;
  
  	initial begin
      	si = 2'b00;
      	//so = 2'b00;
    end
	
  	always @ (posedge clk) begin
      	#10
      	if (so == 2'b00 || so == 2'b01 || so == 2'b10 || so == 2'b11)
       	 	si = so;
      	else
         	si = 2'b00;
	end

endmodule

assignment1_pattern_recognisation/FirstAssignmentBehavioral/outputFn_beh.v
`timescale 1ns / 1ps
//////////////////////////////////////////////////////////////////////////////////
// Company: 
// Engineer: 
// 
// Create Date:    10:58:49 07/28/2017 
// Design Name: 
// Module Name:    outputFn_beh 
// Project Name: 
// Target Devices: 
// Tool versions: 
// Description: 
//
// Dependencies: 
//
// Revision: 
// Revision 0.01 - File Created
// Additional Comments: 
//
//////////////////////////////////////////////////////////////////////////////////
module outputFn_beh ( inp, clk, s, out);

	input inp, clk;
  	input [1:0] s;
	output out;
	
	reg out;
	
  always @ (posedge clk) begin
		if (inp)
			out = (~s[1]) & s[0];
		else
			out = s[1] & s[0];
	end

endmodule

assignment1_pattern_recognisation/FirstAssignmentBehavioral/stateTransFn_beh.v
`timescale 1ns / 1ps
//////////////////////////////////////////////////////////////////////////////////
// Company: 
// Engineer: 
// 
// Create Date:    18:04:57 07/27/2017 
// Design Name: 
// Module Name:    stateTransFn_beh 
// Project Name: 
// Target Devices: 
// Tool versions: 
// Description: 
//
// Dependencies: 
//
// Revision: 
// Revision 0.01 - File Created
// Additional Comments: 
//
//////////////////////////////////////////////////////////////////////////////////
module stateTransFn_beh ( inp, clk, si, so );

	input inp, clk;
	input [1:0] si;
	output [1:0] so;
	
	parameter S0 = 2'b00;
	parameter S1 = 2'b01;
	parameter S2 = 2'b10;
	parameter S3 = 2'b11;
	
	reg [1:0] so;
	
  always @ (posedge clk) begin
		case (si) 
			2'b00 : so = (inp) ? 2'b10 : 2'b01;
			2'b01 : so = (inp) ? 2'b10 : 2'b00;
			2'b10 : so = (inp) ? 2'b11 : 2'b01;
			2'b11 : so = (inp) ? 2'b10 : 2'b01;
          	default : so = 2'b00;
		endcase
	end

endmodule

assignment1_pattern_recognisation/FirstAssignmentBehavioral/fsm_beh.v
`timescale 1ns / 1ps
//////////////////////////////////////////////////////////////////////////////////
// Company: 
// Engineer: 
// 
// Create Date:    11:01:16 07/28/2017 
// Design Name: 
// Module Name:    fsm_beh 
// Project Name: 
// Target Devices: 
// Tool versions: 
// Description: 
//
// Dependencies: 
//
// Revision: 
// Revision 0.01 - File Created
// Additional Comments: 
//
//////////////////////////////////////////////////////////////////////////////////
module fsm_beh (inp, clk, si, so, out);
  
  	input inp, clk;
  	output out;
  	output [1:0] so;
  	output [1:0] si;

	stateTransFn_beh STFB (inp, clk, si, so);
	outputFn_beh OFB (inp, clk, si, out);
	delayElem_beh DEB (si, so, clk);

endmodule

assignment1_pattern_recognisation/FirstAssignmentBehavioral/top.v
`timescale 1ns / 1ps
//////////////////////////////////////////////////////////////////////////////////
// Company: 
// Engineer: 
// 
// Create Date:    11:01:37 07/28/2017 
// Design Name: 
// Module Name:    top 
// Project Name: 
// Target Devices: 
// Tool versions: 
// Description: 
//
// Dependencies: 
//
// Revision: 
// Revision 0.01 - File Created
// Additional Comments: 
//
//////////////////////////////////////////////////////////////////////////////////
module top;

	wire inp, clk, out;
	wire [1:0] si;
	wire [1:0] so;
	
	// assign si = 2'b00;

	fsm_beh FSMB (inp, clk, si, so, out);
	testBench TB (inp, clk);
  
  	initial begin
        $dumpfile("dump.vcd");
        $dumpvars;
    end
	
endmodule

assignment1_pattern_recognisation/FirstAssignmentBehavioral/dump.vcd
$date
   Sat Aug 12 06:16:25 2017
$end
$version
  P.20131013
$end
$timescale
  1ps
$end
$scope module top $end
$var wire 1 4 inp $end
$var wire 1 9 clk $end
$var wire 1 * out $end
$var wire 1 6 si [1] $end
$var wire 1 7 si [0] $end
$var wire 1 : so [1] $end
$var wire 1 ; so [0] $end
$scope module FSMB $end
$var wire 1 4 inp $end
$var wire 1 9 clk $end
$var wire 1 * out $end
$var wire 1 : so [1] $end
$var wire 1 ; so [0] $end
$var wire 1 6 si [1] $end
$var wire 1 7 si [0] $end
$scope module STFB $end
$var wire 1 4 inp $end
$var wire 1 9 clk $end
$var wire 1 6 si [1] $end
$var wire 1 7 si [0] $end
$var reg 2 3 so [1:0] $end
$upscope $end
$scope module OFB $end
$var wire 1 4 inp $end
$var wire 1 9 clk $end
$var wire 1 6 s [1] $end
$var wire 1 7 s [0] $end
$var reg 1 8 out $end
$upscope $end
$scope module DEB $end
$var wire 1 9 clk $end
$var wire 1 : so [1] $end
$var wire 1 ; so [0] $end
$var reg 2 < si [1:0] $end
$upscope $end
$upscope $end
$scope module TB $end
$var integer 32 = seed $end
$var reg 1 > clk $end
$var reg 1 ? inp $end
$upscope $end
$upscope $end
$enddefinitions $end
#0
$dumpvars
bx 3
08
b0 <
b0 =
1>
x?
x4
19
0*
07
06
x;
x:
$end
#250000
0>
09
#500000
b1 3
1>
0?
04
19
1;
0:
#510000
b1 <
17
#750000
0>
09
#1000000
b10 3
18
1>
1?
14
19
1*
0;
1:
#1010000
b10 <
07
16
#1250000
0>
09
#1500000
b11 3
08
1>
19
0*
1;
#1510000
b11 <
17
#1750000
0>
09
#2000000
b10 3
1>
19
0;
#2010000
b10 <
07
#2250000
0>
09
#2500000
b11 3
1>
19
1;
#2510000
b11 <
17
#2750000
0>
09
#3000000
b10 3
1>
19
0;
#3010000
b10 <
07
#3250000
0>
09
#3500000
b11 3
1>
19
1;
#3510000
b11 <
17
#3750000
0>
09
#4000000
b1 3
18
1>
0?
04
19
1*
0:
#4010000
b1 <
06
#4250000
0>
09
#4500000
b10 3
1>
1?
14
19
0;
1:
#4510000
b10 <
07
16
#4750000
0>
09
#5000000
b11 3
08
1>
19
0*
1;
#5010000
b11 <
17
#5250000
0>
09
#5500000
b1 3
18
1>
0?
04
19
1*
0:
#5510000
b1 <
06
#5750000
0>
09
#6000000
b10 3
1>
1?
14
19
0;
1:
#6010000
b10 <
07
16
#6250000
0>
09
#6500000
b11 3
08
1>
19
0*
1;
#6510000
b11 <
17
#6750000
0>
09
#7000000
b1 3
18
1>
0?
04
19
1*
0:
#7010000
b1 <
06
#7250000
0>
09
#7500000
b10 3
1>
1?
14
19
0;
1:
#7510000
b10 <
07
16
#7750000
0>
09
#8000000
b1 3
08
1>
0?
04
19
0*
1;
0:
#8010000
b1 <
17
06
#8250000
0>
09
#8500000
b10 3
18
1>
1?
14
19
1*
0;
1:
#8510000
b10 <
07
16
#8750000
0>
09
#9000000
b1 3
08
1>
0?
04
19
0*
1;
0:
#9010000
b1 <
17
06
#9250000
0>
09
#9500000
b10 3
18
1>
1?
14
19
1*
0;
1:
#9510000
b10 <
07
16
#9750000
0>
09
#10000000
b11 3
08
1>
19
0*
1;
#10010000
b11 <
17
#10250000
0>
09
#10500000
b1 3
18
1>
0?
04
19
1*
0:
#10510000
b1 <
06
#10750000
0>
09
#11000000
b10 3
1>
1?
14
19
0;
1:
#11010000
b10 <
07
16
#11250000
0>
09
#11500000
b1 3
08
1>
0?
04
19
0*
1;
0:
#11510000
b1 <
17
06
#11750000
0>
09
#12000000
b0 3
1>
19
0;
#12010000
b0 <
07
#12250000
0>
09
#12500000
b1 3
1>
19
1;
#12510000
b1 <
17
#12750000
0>
09
#13000000
b10 3
18
1>
1?
14
19
1*
0;
1:
#13010000
b10 <
07
16
#13250000
0>
09
#13500000
b1 3
08
1>
0?
04
19
0*
1;
0:
#13510000
b1 <
17
06
#13750000
0>
09
#14000000
b10 3
18
1>
1?
14
19
1*
0;
1:
#14010000
b10 <
07
16
#14250000
0>
09
#14500000
b11 3
08
1>
19
0*
1;
#14510000
b11 <
17
