assignment1_pattern_recognisation/FirstAssignmentStructural/testBench.v
`timescale 1ns / 1ps
//////////////////////////////////////////////////////////////////////////////////
// Company: 
// Engineer: 
// 
// Create Date:    04:30:20 07/22/2017 
// Design Name: 
// Module Name:    testBench 
// Project Name: 
// Target Devices: 
// Tool versions: 
// Description: 
//
// Dependencies: 
//
// Revision: 
// Revision 0.01 - File Created
// Additional Comments: 
//
//////////////////////////////////////////////////////////////////////////////////
module testBench (inp, clk);

	integer seed;
	output clk;
	output inp;
  
  	reg inp;
  	reg clk;
	
	initial begin
		seed = $stime;
      	clk = 1;
      	#15000 $finish;
	end

	always begin
		#500 inp = $random(seed);
	end
  
  	always begin
      	#250 clk = !clk;
    end

endmodule

assignment1_pattern_recognisation/FirstAssignmentStructural/fsm_struct.v
`timescale 1ns / 1ps
//////////////////////////////////////////////////////////////////////////////////
// Company: 
// Engineer: 
// 
// Create Date:    14:31:37 07/28/2017 
// Design Name: 
// Module Name:    fsm_struct 
// Project Name: 
// Target Devices: 
// Tool versions: 
// Description: 
//
// Dependencies: 
//
// Revision: 
// Revision 0.01 - File Created
// Additional Comments: 
//
//////////////////////////////////////////////////////////////////////////////////
// Code your design here
module fsm_struct (inp, clk, so, out);
  
  	input inp, clk;
  	output out;
  	output [1:0] so;
  	wire [1:0] si;
  
  	wire so0_, so1_;

  	stateTransFn_struct STFB (inp, clk, so, si);
  	outputFn_struct OFB (inp, clk, so, out);
  	d_flip_flop_edge_triggered D1 (so[0], so0_, clk, si[0]);
  	d_flip_flop_edge_triggered D2 (so[1], so1_, clk, si[1]);

endmodule


module stateTransFn_struct ( inp, clk, si, so );

	input inp, clk;
	input [1:0] si;
	output [1:0] so;
	
	nor NG1 (a, inp, si[0]);
	and AG1 (b, ~inp, si[1]);
	and AG2 (c, si[1], ~si[0]);
	
	or OG1 (so[0], a, b, c);
	assign so[1] = inp;

endmodule


module outputFn_struct ( inp, clk, s, out);

	input inp, clk;
  	input [1:0] s;
	output out;
	
	// reg out;
  	wire s1_, i_, a, b;
	
	not NG1 (s1_, s[1]);
	not NG2 (i_, inp);
	
  
  	and AG1 (a, s[0], s1_, inp);
	and AG2 (b, s[0], s[1], i_);
  
  	or OG1 (out, a, b);

endmodule

module d_flip_flop_edge_triggered(Q, Qn, C, D);
   output Q;
   output Qn;
   input  C;
   input  D;

   wire   Cn;   // Control input to the D latch.
   wire   Cnn;  // Control input to the SR latch.
   wire   DQ;   // Output from the D latch, input to the gated SR latch.
   wire   DQn;  // Output from the D latch, input to the gated SR latch.
   
   not(Cn, C);
   not(Cnn, Cn);   
   d_latch dl(DQ, DQn, Cn, D);
   sr_latch_gated sr(Q, Qn, Cnn, DQ, DQn);   
endmodule // d_flip_flop_edge_triggered

module d_latch(Q, Qn, G, D);
   output Q;
   output Qn;
   input  G;   
   input  D;

   wire   Dn; 
   wire   D1;
   wire   Dn1;

   not(Dn, D);   
   and(D1, G, D);
   and(Dn1, G, Dn);   
   nor(Qn, D1, Q);
   nor(Q, Dn1, Qn);
endmodule // d_latch

module sr_latch_gated(Q, Qn, G, S, R);
   output Q;
   output Qn;
   input  G;   
   input  S;
   input  R;

   wire   S1;
   wire   R1;
   
   and(S1, G, S);
   and(R1, G, R);   
   nor(Qn, S1, Q);
   nor(Q, R1, Qn);
endmodule // sr_latch_gated

assignment1_pattern_recognisation/FirstAssignmentStructural/top.v
`timescale 1ns / 1ps
//////////////////////////////////////////////////////////////////////////////////
// Company: 
// Engineer: 
// 
// Create Date:    04:29:03 07/22/2017 
// Design Name: 
// Module Name:    top 
// Project Name: 
// Target Devices: 
// Tool versions: 
// Description: 
//
// Dependencies: 
//
// Revision: 
// Revision 0.01 - File Created
// Additional Comments: 
//
//////////////////////////////////////////////////////////////////////////////////
module top;

	wire inp, clk, out;
	// wire [1:0] si;
	wire [1:0] so;
	
	// assign si = 2'b00;

	fsm_struct FSMB (inp, clk, so, out);
	testBench TB (inp, clk);
  
  	initial begin
        $dumpfile("dump.vcd");
        $dumpvars;
    end
	
endmodule

assignment1_pattern_recognisation/FirstAssignmentStructural/dump.vcd
$date
   Fri Jul 28 16:14:57 2017
$end
$version
  P.20131013
$end
$timescale
  1ps
$end
$scope module top $end
$var wire 1 8 inp $end
$var wire 1 Y clk $end
$var wire 1 < out $end
$var wire 1 f so [1] $end
$var wire 1 P so [0] $end
$scope module FSMB $end
$var wire 1 8 inp $end
$var wire 1 Y clk $end
$var wire 1 < out $end
$var wire 1 f so [1] $end
$var wire 1 P so [0] $end
$var wire 1 b si [1] $end
$var wire 1 L si [0] $end
$var wire 1 Q so0_ $end
$var wire 1 g so1_ $end
$scope module STFB $end
$var wire 1 8 inp $end
$var wire 1 Y clk $end
$var wire 1 f si [1] $end
$var wire 1 P si [0] $end
$var wire 1 b so [1] $end
$var wire 1 L so [0] $end
$var wire 1 5 a $end
$var wire 1 6 b $end
$var wire 1 7 c $end
$upscope $end
$scope module OFB $end
$var wire 1 8 inp $end
$var wire 1 Y clk $end
$var wire 1 f s [1] $end
$var wire 1 P s [0] $end
$var wire 1 < out $end
$var wire 1 = s1_ $end
$var wire 1 > i_ $end
$var wire 1 ? a $end
$var wire 1 @ b $end
$upscope $end
$scope module D1 $end
$var wire 1 P Q $end
$var wire 1 Q Qn $end
$var wire 1 Y C $end
$var wire 1 L D $end
$var wire 1 K Cn $end
$var wire 1 R Cnn $end
$var wire 1 S DQ $end
$var wire 1 T DQn $end
$scope module dl $end
$var wire 1 S Q $end
$var wire 1 T Qn $end
$var wire 1 K G $end
$var wire 1 L D $end
$var wire 1 M Dn $end
$var wire 1 N D1 $end
$var wire 1 O Dn1 $end
$upscope $end
$scope module sr $end
$var wire 1 P Q $end
$var wire 1 Q Qn $end
$var wire 1 R G $end
$var wire 1 S S $end
$var wire 1 T R $end
$var wire 1 U S1 $end
$var wire 1 V R1 $end
$upscope $end
$upscope $end
$scope module D2 $end
$var wire 1 f Q $end
$var wire 1 g Qn $end
$var wire 1 Y C $end
$var wire 1 b D $end
$var wire 1 a Cn $end
$var wire 1 h Cnn $end
$var wire 1 i DQ $end
$var wire 1 j DQn $end
$scope module dl $end
$var wire 1 i Q $end
$var wire 1 j Qn $end
$var wire 1 a G $end
$var wire 1 b D $end
$var wire 1 c Dn $end
$var wire 1 d D1 $end
$var wire 1 e Dn1 $end
$upscope $end
$scope module sr $end
$var wire 1 f Q $end
$var wire 1 g Qn $end
$var wire 1 h G $end
$var wire 1 i S $end
$var wire 1 j R $end
$var wire 1 k S1 $end
$var wire 1 l R1 $end
$upscope $end
$upscope $end
$upscope $end
$scope module TB $end
$var integer 32 m seed $end
$var reg 1 n clk $end
$var reg 1 o inp $end
$upscope $end
$upscope $end
$enddefinitions $end
#0
$dumpvars
0K
1Y
x8
x<
xP
xf
xL
xb
xQ
xg
x5
x6
x7
x=
x>
x?
x@
1R
xS
xT
xM
0N
0O
xU
xV
0a
1h
xi
xj
xc
0d
0e
xk
xl
b0 m
1n
xo
$end
#250000
1K
0Y
0R
xN
xO
0U
0V
1a
0h
xd
xe
0k
0l
0n
#500000
0K
1Y
08
0b
1>
0?
1R
0N
0O
xU
xV
0a
1h
1c
0d
0e
xk
xl
1n
0o
#750000
1K
0Y
0R
xN
xO
0U
0V
1a
0h
0i
1j
1e
0k
0l
0n
#1000000
0K
1Y
18
0f
0L
1b
1g
05
06
07
1=
0>
x?
0@
1R
1M
0N
0O
xU
xV
0a
1h
0c
0e
1l
1n
1o
#1250000
1K
0Y
0R
0S
1T
1O
0U
0V
1a
0h
1i
0j
1d
0l
0n
#1500000
0K
1Y
0<
0P
1f
1L
1Q
0g
17
0=
0?
1R
0M
0O
1V
0a
1h
0d
1k
1n
#1750000
1K
0Y
0R
1S
0T
1N
0V
1a
0h
1d
0k
0n
#2000000
0K
1Y
1P
0L
0Q
07
1R
1M
0N
1U
0a
1h
0d
1k
1n
#2250000
1K
0Y
0R
0S
1T
1O
0U
1a
0h
1d
0k
0n
#2500000
0K
1Y
0P
1L
1Q
17
1R
0M
0O
1V
0a
1h
0d
1k
1n
#2750000
1K
0Y
0R
1S
0T
1N
0V
1a
0h
1d
0k
0n
#3000000
0K
1Y
1P
0L
0Q
07
1R
1M
0N
1U
0a
1h
0d
1k
1n
#3250000
1K
0Y
0R
0S
1T
1O
0U
1a
0h
1d
0k
0n
#3500000
0K
1Y
0P
1L
1Q
17
1R
0M
0O
1V
0a
1h
0d
1k
1n
#3750000
1K
0Y
0R
1S
0T
1N
0V
1a
0h
1d
0k
0n
#4000000
0K
1Y
08
1<
1P
0b
0Q
05
16
07
1>
1@
1R
0N
1U
0a
1h
1c
0d
1k
1n
0o
#4250000
1K
0Y
0R
1N
0U
1a
0h
0i
1j
1e
0k
0n
#4500000
0K
1Y
18
1<
0f
0L
1b
1g
06
1=
0>
1?
0@
1R
1M
0N
1U
0a
1h
0c
0e
1l
1n
1o
#4750000
1K
0Y
0R
0S
1T
1O
0U
1a
0h
1i
0j
1d
0l
0n
#5000000
0K
1Y
0<
0P
1f
1L
1Q
0g
17
0=
0?
1R
0M
0O
1V
0a
1h
0d
1k
1n
#5250000
1K
0Y
0R
1S
0T
1N
0V
1a
0h
1d
0k
0n
#5500000
0K
1Y
08
1<
1P
0b
0Q
05
16
07
1>
1@
1R
0N
1U
0a
1h
1c
0d
1k
1n
0o
#5750000
1K
0Y
0R
1N
0U
1a
0h
0i
1j
1e
0k
0n
#6000000
0K
1Y
18
1<
0f
0L
1b
1g
06
1=
0>
1?
0@
1R
1M
0N
1U
0a
1h
0c
0e
1l
1n
1o
#6250000
1K
0Y
0R
0S
1T
1O
0U
1a
0h
1i
0j
1d
0l
0n
#6500000
0K
1Y
0<
0P
1f
1L
1Q
0g
17
0=
0?
1R
0M
0O
1V
0a
1h
0d
1k
1n
#6750000
1K
0Y
0R
1S
0T
1N
0V
1a
0h
1d
0k
0n
#7000000
0K
1Y
08
1<
1P
0b
0Q
05
16
07
1>
1@
1R
0N
1U
0a
1h
1c
0d
1k
1n
0o
#7250000
1K
0Y
0R
1N
0U
1a
0h
0i
1j
1e
0k
0n
#7500000
0K
1Y
18
1<
0f
0L
1b
1g
06
1=
0>
1?
0@
1R
1M
0N
1U
0a
1h
0c
0e
1l
1n
1o
#7750000
1K
0Y
0R
0S
1T
1O
0U
1a
0h
1i
0j
1d
0l
0n
#8000000
0K
1Y
08
0<
0P
1f
1L
0b
1Q
0g
15
16
17
0=
1>
0?
1R
0M
0O
1V
0a
1h
1c
0d
1k
1n
0o
#8250000
1K
0Y
0R
1S
0T
1N
0V
1a
0h
0i
1j
1e
0k
0n
#8500000
0K
1Y
18
1<
1P
0f
0L
1b
0Q
1g
05
06
07
1=
0>
1?
1R
1M
0N
1U
0a
1h
0c
0e
1l
1n
1o
#8750000
1K
0Y
0R
0S
1T
1O
0U
1a
0h
1i
0j
1d
0l
0n
#9000000
0K
1Y
08
0<
0P
1f
1L
0b
1Q
0g
15
16
17
0=
1>
0?
1R
0M
0O
1V
0a
1h
1c
0d
1k
1n
0o
#9250000
1K
0Y
0R
1S
0T
1N
0V
1a
0h
0i
1j
1e
0k
0n
#9500000
0K
1Y
18
1<
1P
0f
0L
1b
0Q
1g
05
06
07
1=
0>
1?
1R
1M
0N
1U
0a
1h
0c
0e
1l
1n
1o
#9750000
1K
0Y
0R
0S
1T
1O
0U
1a
0h
1i
0j
1d
0l
0n
#10000000
0K
1Y
0<
0P
1f
1L
1Q
0g
17
0=
0?
1R
0M
0O
1V
0a
1h
0d
1k
1n
#10250000
1K
0Y
0R
1S
0T
1N
0V
1a
0h
1d
0k
0n
#10500000
0K
1Y
08
1<
1P
0b
0Q
05
16
07
1>
1@
1R
0N
1U
0a
1h
1c
0d
1k
1n
0o
#10750000
1K
0Y
0R
1N
0U
1a
0h
0i
1j
1e
0k
0n
#11000000
0K
1Y
18
1<
0f
0L
1b
1g
06
1=
0>
1?
0@
1R
1M
0N
1U
0a
1h
0c
0e
1l
1n
1o
#11250000
1K
0Y
0R
0S
1T
1O
0U
1a
0h
1i
0j
1d
0l
0n
#11500000
0K
1Y
08
0<
0P
1f
1L
0b
1Q
0g
15
16
17
0=
1>
0?
1R
0M
0O
1V
0a
1h
1c
0d
1k
1n
0o
#11750000
1K
0Y
0R
1S
0T
1N
0V
1a
0h
0i
1j
1e
0k
0n
#12000000
0K
1Y
1P
0f
0L
0Q
1g
05
06
07
1=
1R
1M
0N
1U
0a
1h
0e
1l
1n
#12250000
1K
0Y
0R
0S
1T
1O
0U
1a
0h
1e
0l
0n
#12500000
0K
1Y
0P
1L
1Q
15
1R
0M
0O
1V
0a
1h
0e
1l
1n
#12750000
1K
0Y
0R
1S
0T
1N
0V
1a
0h
1e
0l
0n
#13000000
0K
1Y
18
1<
1P
0L
1b
0Q
05
0>
1?
1R
1M
0N
1U
0a
1h
0c
0e
1l
1n
1o
#13250000
1K
0Y
0R
0S
1T
1O
0U
1a
0h
1i
0j
1d
0l
0n
#13500000
0K
1Y
08
0<
0P
1f
1L
0b
1Q
0g
15
16
17
0=
1>
0?
1R
0M
0O
1V
0a
1h
1c
0d
1k
1n
0o
#13750000
1K
0Y
0R
1S
0T
1N
0V
1a
0h
0i
1j
1e
0k
0n
#14000000
0K
1Y
18
1<
1P
0f
0L
1b
0Q
1g
05
06
07
1=
0>
1?
1R
1M
0N
1U
0a
1h
0c
0e
1l
1n
1o
#14250000
1K
0Y
0R
0S
1T
1O
0U
1a
0h
1i
0j
1d
0l
0n
#14500000
0K
1Y
0<
0P
1f
1L
1Q
0g
17
0=
0?
1R
0M
0O
1V
0a
1h
0d
1k
1n
#14750000
1K
0Y
0R
1S
0T
1N
0V
1a
0h
1d
0k
0n
